exp_mixture_model/EMM.py
exp_mixture_model/__init__.py
exp_mixture_model/__version__.py
exp_mixture_model-1.0.0.dist-info/LICENSE.txt
exp_mixture_model-1.0.0.dist-info/METADATA
exp_mixture_model-1.0.0.dist-info/WHEEL
exp_mixture_model-1.0.0.dist-info/top_level.txt
exp_mixture_model-1.0.0.dist-info/RECORD
