Metadata-Version: 2.1
Name: exp-mixture-model
Version: 1.0.0
Summary: Maximum likelihood estimation and model selection of EMMs
Home-page: https://github.com/naokimas/exp_mixture_model
Author: Makoto Okada, Kenji Yamanishi and Naoki Masuda
Author-email: naoki.masuda@bristol.ac.uk
License: MIT License
Keywords: exponential mixture model,model selection,normalized maximum likelihood
Platform: UNKNOWN
Classifier: Development Status :: 3 - Alpha
Classifier: Intended Audience :: Science/Research
Classifier: Topic :: Software Development
Classifier: License :: OSI Approved :: MIT License
Classifier: Programming Language :: Python
Classifier: Programming Language :: Python :: 3
Classifier: Programming Language :: Python :: 3.4
Classifier: Programming Language :: Python :: 3.5
Classifier: Programming Language :: Python :: 3.6
Classifier: Programming Language :: Python :: 3.7
Requires-Dist: numpy
Requires-Dist: scipy
Requires-Dist: pandas
Requires-Dist: matplotlib
